{
  "universe_usage_history": [
    {
      "assignment_id": "quartznet-dashboard-2026-02-16",
      "universe": "The Usual Suspects",
      "timestamp": "2026-02-16T18:27:12Z"
    }
  ],
  "assignment_cast_snapshots": {
    "quartznet-dashboard-2026-02-16": {
      "universe": "The Usual Suspects",
      "agent_map": {
        "keaton": "Keaton",
        "mcmanus": "McManus",
        "fenster": "Fenster",
        "hockney": "Hockney",
        "verbal": "Verbal"
      },
      "created_at": "2026-02-16T18:27:12Z"
    }
  }
}
